Workbook

Sheet SKU Master
A1: SKU | B1: UPC (fictional) | C1: Department | D1: Category | E1: Brand | F1: Description | G1: Pack Size | H1: UOM | I1: Retail Price | J1: Case Pack | K1: Private Label | L1: Perishable | M1: Sales Velocity (units/store/wk) | N1: Reorder Point (units)
A2: 07-00001 | B2: 106992768117 | C2: =VLOOKUP($B2,'Product Master'!$A$2:$O$5991,7,FALSE()) -> Dry Grocery | D2: =VLOOKUP($B2,'Product Master'!$A$2:$O$5991,8,FALSE()) -> Ready-to-Eat Cereal | E2: =VLOOKUP($B2,'Product Master'!$A$2:$O$5991,5,FALSE()) -> Redbarn | F2: =VLOOKUP($B2,'Product Master'!$A$2:$O$5991,4,FALSE()) -> Redbarn Reduced Sugar Granola Clusters, 18 oz | G2: =VLOOKUP($B2,'Product Master'!$A$2:$O$5991,9,FALSE()) -> 18 oz | H2: each | I2: =VLOOKUP($B2,'Product Master'!$A$2:$O$5991,14,FALSE()) -> 4.99 | J2: =VLOOKUP($B2,'Product Master'!$A$2:$O$5991,13,FALSE()) -> 6 | K2: =VLOOKUP($B2,'Product Master'!$A$2:$O$5991,11,FALSE()) -> N | L2: =VLOOKUP($B2,'Product Master'!$A$2:$O$5991,12,FALSE()) -> N | M2: 8 | N2: 30
A3: 07-00002 | B3: 011312704937 | C3: =VLOOKUP($B3,'Product Master'!$A$2:$O$5991,7,FALSE()) -> Dry Grocery | D3: =VLOOKUP($B3,'Product Master'!$A$2:$O$5991,8,FALSE()) -> Ready-to-Eat Cereal | E3: =VLOOKUP($B3,'Product Master'!$A$2:$O$5991,5,FALSE()) -> Wheatstone | F3: =VLOOKUP($B3,'Product Master'!$A$2:$O$5991,4,FALSE()) -> Wheatstone Honey Bran Flakes, 12 oz | G3: =VLOOKUP($B3,'Product Master'!$A$2:$O$5991,9,FALSE()) -> 12 oz | H3: each | I3: =VLOOKUP($B3,'Product Master'!$A$2:$O$5991,14,FALSE()) -> 5.99 | J3: =VLOOKUP($B3,'Product Master'!$A$2:$O$5991,13,FALSE()) -> 1 | K3: =VLOOKUP($B3,'Product Master'!$A$2:$O$5991,11,FALSE()) -> N | L3: =VLOOKUP($B3,'Product Master'!$A$2:$O$5991,12,FALSE()) -> N | M3: 17 | N3: 26
A4: 07-00003 | B4: 214877400000 | C4: =VLOOKUP($B4,'Product Master'!$A$2:$O$5991,7,FALSE()) -> Dry Grocery | D4: =VLOOKUP($B4,'Product Master'!$A$2:$O$5991,8,FALSE()) -> Ready-to-Eat Cereal | E4: =VLOOKUP($B4,'Product Master'!$A$2:$O$5991,5,FALSE()) -> Roastport | F4: =VLOOKUP($B4,'Product Master'!$A$2:$O$5991,4,FALSE()) -> Roastport Cinnamon Oat Rounds, 24 oz | G4: =VLOOKUP($B4,'Product Master'!$A$2:$O$5991,9,FALSE()) -> 24 oz | H4: each | I4: =VLOOKUP($B4,'Product Master'!$A$2:$O$5991,14,FALSE()) -> 6.89 | J4: =VLOOKUP($B4,'Product Master'!$A$2:$O$5991,13,FALSE()) -> 24 | K4: =VLOOKUP($B4,'Product Master'!$A$2:$O$5991,11,FALSE()) -> N | L4: =VLOOKUP($B4,'Product Master'!$A$2:$O$5991,12,FALSE()) -> N | M4: 25 | N4: 27
A5: 07-00004 | B5: 492790559772 | C5: =VLOOKUP($B5,'Product Master'!$A$2:$O$5991,7,FALSE()) -> Dry Grocery | D5: =VLOOKUP($B5,'Product Master'!$A$2:$O$5991,8,FALSE()) -> Ready-to-Eat Cereal | E5: =VLOOKUP($B5,'Product Master'!$A$2:$O$5991,5,FALSE()) -> Redbarn | F5: =VLOOKUP($B5,'Product Master'!$A$2:$O$5991,4,FALSE()) -> Redbarn Frosted Bran Flakes, 10.5 oz | G5: =VLOOKUP($B5,'Product Master'!$A$2:$O$5991,9,FALSE()) -> 10.5 oz | H5: each | I5: =VLOOKUP($B5,'Product Master'!$A$2:$O$5991,14,FALSE()) -> 3.49 | J5: =VLOOKUP($B5,'Product Master'!$A$2:$O$5991,13,FALSE()) -> 4 | K5: =VLOOKUP($B5,'Product Master'!$A$2:$O$5991,11,FALSE()) -> N | L5: =VLOOKUP($B5,'Product Master'!$A$2:$O$5991,12,FALSE()) -> N | M5: 97 | N5: 13
A6: 07-00005 | B6: 676749544099 | C6: =VLOOKUP($B6,'Product Master'!$A$2:$O$5991,7,FALSE()) -> Dry Grocery | D6: =VLOOKUP($B6,'Product Master'!$A$2:$O$5991,8,FALSE()) -> Ready-to-Eat Cereal | E6: =VLOOKUP($B6,'Product Master'!$A$2:$O$5991,5,FALSE()) -> Roastport | F6: =VLOOKUP($B6,'Product Master'!$A$2:$O$5991,4,FALSE()) -> Roastport Frosted Honey Clusters, 18 oz | G6: =VLOOKUP($B6,'Product Master'!$A$2:$O$5991,9,FALSE()) -> 18 oz | H6: each | I6: =VLOOKUP($B6,'Product Master'!$A$2:$O$5991,14,FALSE()) -> 4.39 | J6: =VLOOKUP($B6,'Product Master'!$A$2:$O$5991,13,FALSE()) -> 12 | K6: =VLOOKUP($B6,'Product Master'!$A$2:$O$5991,11,FALSE()) -> N | L6: =VLOOKUP($B6,'Product Master'!$A$2:$O$5991,12,FALSE()) -> N | M6: 8 | N6: 12
A7: 07-00006 | B7: 496366693740 | C7: =VLOOKUP($B7,'Product Master'!$A$2:$O$5991,7,FALSE()) -> Dry Grocery | D7: =VLOOKUP($B7,'Product Master'!$A$2:$O$5991,8,FALSE()) -> Ready-to-Eat Cereal | E7: =VLOOKUP($B7,'Product Master'!$A$2:$O$5991,5,FALSE()) -> Golden Grain Co. | F7: =VLOOKUP($B7,'Product Master'!$A$2:$O$5991,4,FALSE()) -> Golden Grain Co. Rice Puffs, 12 oz | G7: =VLOOKUP($B7,'Product Master'!$A$2:$O$5991,9,FALSE()) -> 12 oz | H7: each | I7: =VLOOKUP($B7,'Product Master'!$A$2:$O$5991,14,FALSE()) -> 4.29 | J7: =VLOOKUP($B7,'Product Master'!$A$2:$O$5991,13,FALSE()) -> 8 | K7: =VLOOKUP($B7,'Product Master'!$A$2:$O$5991,11,FALSE()) -> N | L7: =VLOOKUP($B7,'Product Master'!$A$2:$O$5991,12,FALSE()) -> N | M7: 113 | N7: 13
A8: 07-00007 | B8: 042924875818 | C8: =VLOOKUP($B8,'Product Master'!$A$2:$O$5991,7,FALSE()) -> Dry Grocery | D8: =VLOOKUP($B8,'Product Master'!$A$2:$O$5991,8,FALSE()) -> Ready-to-Eat Cereal | E8: =VLOOKUP($B8,'Product Master'!$A$2:$O$5991,5,FALSE()) -> Orchard Spread | F8: =VLOOKUP($B8,'Product Master'!$A$2:$O$5991,4,FALSE()) -> Orchard Spread Frosted Oat Rounds, 12 oz | G8: =VLOOKUP($B8,'Product Master'!$A$2:$O$5991,9,FALSE()) -> 12 oz | H8: each | I8: =VLOOKUP($B8,'Product Master'!$A$2:$O$5991,14,FALSE()) -> 5.79 | J8: =VLOOKUP($B8,'Product Master'!$A$2:$O$5991,13,FALSE()) -> 8 | K8: =VLOOKUP($B8,'Product Master'!$A$2:$O$5991,11,FALSE()) -> N | L8: =VLOOKUP($B8,'Product Master'!$A$2:$O$5991,12,FALSE()) -> N | M8: 56 | N8: 17
A9: 07-00008 | B9: 906734906781 | C9: =VLOOKUP($B9,'Product Master'!$A$2:$O$5991,7,FALSE()) -> Dry Grocery | D9: =VLOOKUP($B9,'Product Master'!$A$2:$O$5991,8,FALSE()) -> Ready-to-Eat Cereal | E9: =VLOOKUP($B9,'Product Master'!$A$2:$O$5991,5,FALSE()) -> Wheatstone | F9: =VLOOKUP($B9,'Product Master'!$A$2:$O$5991,4,FALSE()) -> Wheatstone Cinnamon Multigrain Flakes, 18 oz | G9: =VLOOKUP($B9,'Product Master'!$A$2:$O$5991,9,FALSE()) -> 18 oz | H9: each | I9: =VLOOKUP($B9,'Product Master'!$A$2:$O$5991,14,FALSE()) -> 5.29 | J9: =VLOOKUP($B9,'Product Master'!$A$2:$O$5991,13,FALSE()) -> 4 | K9: =VLOOKUP($B9,'Product Master'!$A$2:$O$5991,11,FALSE()) -> N | L9: =VLOOKUP($B9,'Product Master'!$A$2:$O$5991,12,FALSE()) -> N | M9: 21 | N9: 17
A10: 07-00009 | B10: 984857893333 | C10: =VLOOKUP($B10,'Product Master'!$A$2:$O$5991,7,FALSE()) -> Dry Grocery | D10: =VLOOKUP($B10,'Product Master'!$A$2:$O$5991,8,FALSE()) -> Ready-to-Eat Cereal | E10: =VLOOKUP($B10,'Product Master'!$A$2:$O$5991,5,FALSE()) -> Kettle Row | F10: =VLOOKUP($B10,'Product Master'!$A$2:$O$5991,4,FALSE()) -> Kettle Row Granola Clusters, 10.5 oz | G10: =VLOOKUP($B10,'Product Master'!$A$2:$O$5991,9,FALSE()) -> 10.5 oz | H10: each | I10: =VLOOKUP($B10,'Product Master'!$A$2:$O$5991,14,FALSE()) -> 3.89 | J10: =VLOOKUP($B10,'Product Master'!$A$2:$O$5991,13,FALSE()) -> 6 | K10: =VLOOKUP($B10,'Product Master'!$A$2:$O$5991,11,FALSE()) -> N | L10: =VLOOKUP($B10,'Product Master'!$A$2:$O$5991,12,FALSE()) -> N | M10: 79 | N10: 26
A11: 07-00010 | B11: 956823075157 | C11: =VLOOKUP($B11,'Product Master'!$A$2:$O$5991,7,FALSE()) -> Dry Grocery | D11: =VLOOKUP($B11,'Product Master'!$A$2:$O$5991,8,FALSE()) -> Ready-to-Eat Cereal | E11: =VLOOKUP($B11,'Product Master'!$A$2:$O$5991,5,FALSE()) -> Nutgrove | F11: =VLOOKUP($B11,'Product Master'!$A$2:$O$5991,4,FALSE()) -> Nutgrove Honey Oat Rounds, 12 oz | G11: =VLOOKUP($B11,'Product Master'!$A$2:$O$5991,9,FALSE()) -> 12 oz | H11: each | I11: =VLOOKUP($B11,'Product Master'!$A$2:$O$5991,14,FALSE()) -> 5.99 | J11: =VLOOKUP($B11,'Product Master'!$A$2:$O$5991,13,FALSE()) -> 8 | K11: =VLOOKUP($B11,'Product Master'!$A$2:$O$5991,11,FALSE()) -> N | L11: =VLOOKUP($B11,'Product Master'!$A$2:$O$5991,12,FALSE()) -> N | M11: 85 | N11: 4
A12: 07-00011 | B12: 489010397993 | C12: =VLOOKUP($B12,'Product Master'!$A$2:$O$5991,7,FALSE()) -> Dry Grocery | D12: =VLOOKUP($B12,'Product Master'!$A$2:$O$5991,8,FALSE()) -> Ready-to-Eat Cereal | E12: =VLOOKUP($B12,'Product Master'!$A$2:$O$5991,5,FALSE()) -> Golden Grain Co. | F12: =VLOOKUP($B12,'Product Master'!$A$2:$O$5991,4,FALSE()) -> Golden Grain Co. Cinnamon Oat Rounds, 14 oz | G12: =VLOOKUP($B12,'Product Master'!$A$2:$O$5991,9,FALSE()) -> 14 oz | H12: each | I12: =VLOOKUP($B12,'Product Master'!$A$2:$O$5991,14,FALSE()) -> 4.29 | J12: =VLOOKUP($B12,'Product Master'!$A$2:$O$5991,13,FALSE()) -> 4 | K12: =VLOOKUP($B12,'Product Master'!$A$2:$O$5991,11,FALSE()) -> N | L12: =VLOOKUP($B12,'Product Master'!$A$2:$O$5991,12,FALSE()) -> N | M12: 114 | N12: 9
A13: 07-00012 | B13: 992405326100 | C13: =VLOOKUP($B13,'Product Master'!$A$2:$O$5991,7,FALSE()) -> Dry Grocery | D13: =VLOOKUP($B13,'Product Master'!$A$2:$O$5991,8,FALSE()) -> Ready-to-Eat Cereal | E13: =VLOOKUP($B13,'Product Master'!$A$2:$O$5991,5,FALSE()) -> Thrift Row | F13: =VLOOKUP($B13,'Product Master'!$A$2:$O$5991,4,FALSE()) -> Thrift Row Honey Wheat Squares, 14 oz | G13: =VLOOKUP($B13,'Product Master'!$A$2:$O$5991,9,FALSE()) -> 14 oz | H13: each | I13: =VLOOKUP($B13,'Product Master'!$A$2:$O$5991,14,FALSE()) -> 3.29 | J13: =VLOOKUP($B13,'Product Master'!$A$2:$O$5991,13,FALSE()) -> 6 | K13: =VLOOKUP($B13,'Product Master'!$A$2:$O$5991,11,FALSE()) -> Y | L13: =VLOOKUP($B13,'Product Master'!$A$2:$O$5991,12,FALSE()) -> N | M13: 122 | N13: 34
... A5991: 17-00030 | B5991: 969395624026 | C5991: =VLOOKUP($B5991,'Product Master'!$A$2:$O$5991,7,FALSE()) -> Floral | D5991: =VLOOKUP($B5991,'Product Master'!$A$2:$O$5991,8,FALSE()) -> Potted Plants | E5991: =VLOOKUP($B5991,'Product Master'!$A$2:$O$5991,5,FALSE()) -> Petal & Stem | F5991: =VLOOKUP($B5991,'Product Master'!$A$2:$O$5991,4,FALSE()) -> Petal & Stem Peace Lily, 4 in | G5991: =VLOOKUP($B5991,'Product Master'!$A$2:$O$5991,9,FALSE()) -> 4 in | H5991: each | I5991: =VLOOKUP($B5991,'Product Master'!$A$2:$O$5991,14,FALSE()) -> 8.89 | J5991: =VLOOKUP($B5991,'Product Master'!$A$2:$O$5991,13,FALSE()) -> 1 | K5991: =VLOOKUP($B5991,'Product Master'!$A$2:$O$5991,11,FALSE()) -> N | L5991: =VLOOKUP($B5991,'Product Master'!$A$2:$O$5991,12,FALSE()) -> Y | M5991: 230 | N5991: 10

Sheet Category Space Allocation
A1: Department | B1: Category | C1: Temperature Zone | D1: Fixture Type | E1: Secured/Locked Case Required (Y/N) | F1: Category Role | G1: SKU Count | H1: Avg Facings per SKU | I1: Min Facings per SKU | J1: Max Facings per SKU | K1: Allocated Linear Space (ft) | L1: Unallocated Linear Space (ft) | M1: Total Category Linear Space (ft) | N1: Space Utilization (%) | O1: Sales per Linear Ft per Week ($) | P1: Space Elasticity Coefficient | Q1: Category Captain (Y/N) | R1: Private Label Space Target (%) | S1: Last Reset Date | T1: Reset Cycle (months)
A2: Baby Care | B2: Baby Food | C2: Ambient | D2: Gondola Shelving | E2: N | F2: Routine | G2: 21 | H2: 3.7 | I2: 1 | J2: 6 | K2: 27.2 | L2: 1.9 | M2: =K2+L2 -> 29.1 | N2: =K2/M2 -> 0.9347079 | O2: 18.45 | P2: 0.3 | Q2: N | R2: 20.6 | S2: 2025-12-14 | T2: 20
A3: Baby Care | B3: Diapers | C3: Ambient | D3: Gondola Shelving | E3: N | F3: Routine | G3: 22 | H3: 4.3 | I3: 1 | J3: 8 | K3: 33.1 | L3: 2.4 | M3: =K3+L3 -> 35.5 | N3: =K3/M3 -> 0.93239437 | O3: 15.85 | P3: 0.53 | Q3: Y | R3: 38.6 | S3: 2026-01-31 | T3: 24
A4: Baby Care | B4: Formula | C4: Ambient | D4: Gondola Shelving | E4: Y | F4: Routine | G4: 21 | H4: 4.7 | I4: 1 | J4: 7 | K4: 34.5 | L4: 1.6 | M4: =K4+L4 -> 36.1 | N4: =K4/M4 -> 0.95567867 | O4: 17.62 | P4: 0.45 | Q4: N | R4: 39.4 | S4: 2026-04-21 | T4: 14
A5: Baby Care | B5: Wipes | C5: Ambient | D5: Gondola Shelving | E5: N | F5: Routine | G5: 21 | H5: 3.2 | I5: 1 | J5: 6 | K5: 23.5 | L5: 1.4 | M5: =K5+L5 -> 24.9 | N5: =K5/M5 -> 0.9437751 | O5: 28.13 | P5: 0.41 | Q5: N | R5: 30.1 | S5: 2026-01-09 | T5: 24
A6: Bakery | B6: Bread | C6: Ambient | D6: Bakery Case/Shelving | E6: N | F6: Destination | G6: 18 | H6: 6.5 | I6: 1 | J6: 9 | K6: 40.9 | L6: 2.2 | M6: =K6+L6 -> 43.1 | N6: =K6/M6 -> 0.94895592 | O6: 30.55 | P6: 0.45 | Q6: N | R6: 40.3 | S6: 2026-03-28 | T6: 12
A7: Bakery | B7: Cakes & Desserts | C7: Ambient | D7: Bakery Case/Shelving | E7: N | F7: Destination | G7: 17 | H7: 6.3 | I7: 1 | J7: 10 | K7: 37.5 | L7: 1.4 | M7: =K7+L7 -> 38.9 | N7: =K7/M7 -> 0.96401028 | O7: 63.57 | P7: 0.11 | Q7: N | R7: 33.8 | S7: 2025-07-26 | T7: 18
A8: Bakery | B8: Cookies & Pastries | C8: Ambient | D8: Bakery Case/Shelving | E8: N | F8: Destination | G8: 17 | H8: 5.8 | I8: 1 | J8: 9 | K8: 34.5 | L8: 2 | M8: =K8+L8 -> 36.5 | N8: =K8/M8 -> 0.94520548 | O8: 43 | P8: 0.15 | Q8: N | R8: 27.5 | S8: 2026-07-28 | T8: 12
A9: Bakery | B9: Rolls & Buns | C9: Ambient | D9: Bakery Case/Shelving | E9: N | F9: Destination | G9: 18 | H9: 5.9 | I9: 1 | J9: 10 | K9: 37.2 | L9: 2.5 | M9: =K9+L9 -> 39.7 | N9: =K9/M9 -> 0.93702771 | O9: 44.16 | P9: 0.2 | Q9: N | R9: 45.4 | S9: 2026-07-17 | T9: 18
A10: Beer & Wine | B10: Craft & Import Beer | C10: Refrigerated | D10: Reach-In Cooler | E10: N | F10: Destination | G10: 43 | H10: 6.5 | I10: 1 | J10: 10 | K10: 78.3 | L10: 2.9 | M10: =K10+L10 -> 81.2 | N10: =K10/M10 -> 0.96428571 | O10: 43.59 | P10: 0.09 | Q10: N | R10: 0.9 | S10: 2025-06-23 | T10: 16
A11: Beer & Wine | B11: Domestic Beer | C11: Refrigerated | D11: Reach-In Cooler | E11: N | F11: Routine | G11: 43 | H11: 4.2 | I11: 1 | J11: 6 | K11: 50.6 | L11: 2.7 | M11: =K11+L11 -> 53.3 | N11: =K11/M11 -> 0.94934334 | O11: 37.82 | P11: 0.44 | Q11: Y | R11: 0 | S11: 2026-04-14 | T11: 12
A12: Beer & Wine | B12: Red Wine | C12: Ambient | D12: Gondola Shelving | E12: N | F12: Destination | G12: 42 | H12: 6.8 | I12: 1 | J12: 9 | K12: 80 | L12: 4 | M12: =K12+L12 -> 84 | N12: =K12/M12 -> 0.95238095 | O12: 41.66 | P12: 0.5 | Q12: N | R12: 0 | S12: 2026-04-29 | T12: 16
A13: Beer & Wine | B13: White Wine | C13: Refrigerated | D13: Reach-In Cooler | E13: N | F13: Routine | G13: 42 | H13: 3.2 | I13: 1 | J13: 6 | K13: 37.6 | L13: 1.2 | M13: =K13+L13 -> 38.8 | N13: =K13/M13 -> 0.96907216 | O13: 43.75 | P13: 0.19 | Q13: N | R13: 1 | S13: 2025-04-06 | T13: 18
... A118: Produce | B118: Packaged Salads | C118: Refrigerated | D118: Reach-In Cooler | E118: N | F118: Destination | G118: 23 | H118: 5.3 | I118: 1 | J118: 8 | K118: 42.7 | L118: 2.6 | M118: =K118+L118 -> 45.3 | N118: =K118/M118 -> 0.94260486 | O118: 48.72 | P118: 0.37 | Q118: N | R118: 21.4 | S118: 2026-01-26 | T118: 12

Sheet SKU Merchandising Attributes
A1: SKU | B1: Description | C1: Package Width (in) | D1: Package Height (in) | E1: Package Depth (in) | F1: Shelf Orientation | G1: Stackable (Y/N) | H1: Unit Cost ($) | I1: Gross Margin (%) | J1: Current Facings Assigned | K1: Current Linear Space Assigned (in) | L1: Assortment Status | M1: Seasonality Window | N1: Age-Restricted (Y/N) | O1: Allergen Flag | P1: Shelf Level Assigned | Q1: Secondary/Impulse Display Eligible (Y/N)
A2: ='SKU Master'!A2 -> 07-00001 | B2: =VLOOKUP(A2,'SKU Master'!$A:$N,6,FALSE()) -> Redbarn Reduced Sugar Granola Clusters, 18 oz | C2: 3.5 | D2: 4.9 | E2: 4.8 | F2: Upright | G2: Y | H2: 3.38 | I2: =('SKU Master'!I2-H2)/'SKU Master'!I2 -> 0.32264529 | J2: 1 | K2: =J2*C2 -> 3.5 | L2: Delist Candidate | M2: Year-Round | N2: N | O2: Contains Gluten | P2: Top | Q2: N
A3: ='SKU Master'!A3 -> 07-00002 | B3: =VLOOKUP(A3,'SKU Master'!$A:$N,6,FALSE()) -> Wheatstone Honey Bran Flakes, 12 oz | C3: 2.8 | D3: 9 | E3: 2.8 | F3: Upright | G3: Y | H3: 3.84 | I3: =('SKU Master'!I3-H3)/'SKU Master'!I3 -> 0.35893155 | J3: 1 | K3: =J3*C3 -> 2.8 | L3: Core | M3: Year-Round | N3: N | O3: Contains Gluten | P3: Top | Q3: N
A4: ='SKU Master'!A4 -> 07-00003 | B4: =VLOOKUP(A4,'SKU Master'!$A:$N,6,FALSE()) -> Roastport Cinnamon Oat Rounds, 24 oz | C4: 3.3 | D4: 4.6 | E4: 4.6 | F4: Upright | G4: Y | H4: 4.87 | I4: =('SKU Master'!I4-H4)/'SKU Master'!I4 -> 0.29317852 | J4: 2 | K4: =J4*C4 -> 6.6 | L4: Core | M4: Year-Round | N4: N | O4: Contains Gluten | P4: Top | Q4: N
A5: ='SKU Master'!A5 -> 07-00004 | B5: =VLOOKUP(A5,'SKU Master'!$A:$N,6,FALSE()) -> Redbarn Frosted Bran Flakes, 10.5 oz | C5: 3 | D5: 8.6 | E5: 5 | F5: Upright | G5: N | H5: 2.04 | I5: =('SKU Master'!I5-H5)/'SKU Master'!I5 -> 0.41547278 | J5: 5 | K5: =J5*C5 -> 15 | L5: Core | M5: Year-Round | N5: N | O5: Contains Gluten | P5: Middle | Q5: N
A6: ='SKU Master'!A6 -> 07-00005 | B6: =VLOOKUP(A6,'SKU Master'!$A:$N,6,FALSE()) -> Roastport Frosted Honey Clusters, 18 oz | C6: 3.5 | D6: 6.5 | E6: 3.7 | F6: Upright | G6: Y | H6: 2.62 | I6: =('SKU Master'!I6-H6)/'SKU Master'!I6 -> 0.40318907 | J6: 2 | K6: =J6*C6 -> 7 | L6: Delist Candidate | M6: Year-Round | N6: N | O6: Contains Gluten | P6: Top | Q6: N
A7: ='SKU Master'!A7 -> 07-00006 | B7: =VLOOKUP(A7,'SKU Master'!$A:$N,6,FALSE()) -> Golden Grain Co. Rice Puffs, 12 oz | C7: 4.1 | D7: 8.4 | E7: 2.8 | F7: Upright | G7: Y | H7: 2.69 | I7: =('SKU Master'!I7-H7)/'SKU Master'!I7 -> 0.37296037 | J7: 6 | K7: =J7*C7 -> 24.6 | L7: Core | M7: Year-Round | N7: N | O7: Contains Gluten | P7: Eye-Level | Q7: N
A8: ='SKU Master'!A8 -> 07-00007 | B8: =VLOOKUP(A8,'SKU Master'!$A:$N,6,FALSE()) -> Orchard Spread Frosted Oat Rounds, 12 oz | C8: 3.8 | D8: 8.3 | E8: 4.3 | F8: Upright | G8: Y | H8: 3.85 | I8: =('SKU Master'!I8-H8)/'SKU Master'!I8 -> 0.33506045 | J8: 3 | K8: =J8*C8 -> 11.4 | L8: Core | M8: Year-Round | N8: N | O8: Contains Gluten | P8: Bottom | Q8: N
A9: ='SKU Master'!A9 -> 07-00008 | B9: =VLOOKUP(A9,'SKU Master'!$A:$N,6,FALSE()) -> Wheatstone Cinnamon Multigrain Flakes, 18 oz | C9: 3.6 | D9: 7.8 | E9: 4.5 | F9: Upright | G9: Y | H9: 3.53 | I9: =('SKU Master'!I9-H9)/'SKU Master'!I9 -> 0.33270321 | J9: 2 | K9: =J9*C9 -> 7.2 | L9: Core | M9: Year-Round | N9: N | O9: Contains Gluten | P9: Top | Q9: N
A10: ='SKU Master'!A10 -> 07-00009 | B10: =VLOOKUP(A10,'SKU Master'!$A:$N,6,FALSE()) -> Kettle Row Granola Clusters, 10.5 oz | C10: 4.8 | D10: 8.1 | E10: 2.6 | F10: Upright | G10: N | H10: 2.54 | I10: =('SKU Master'!I10-H10)/'SKU Master'!I10 -> 0.3470437 | J10: 5 | K10: =J10*C10 -> 24 | L10: Core | M10: Year-Round | N10: N | O10: Contains Gluten | P10: Middle | Q10: N
A11: ='SKU Master'!A11 -> 07-00010 | B11: =VLOOKUP(A11,'SKU Master'!$A:$N,6,FALSE()) -> Nutgrove Honey Oat Rounds, 12 oz | C11: 3.2 | D11: 6.8 | E11: 4.4 | F11: Upright | G11: Y | H11: 3.94 | I11: =('SKU Master'!I11-H11)/'SKU Master'!I11 -> 0.34223706 | J11: 4 | K11: =J11*C11 -> 12.8 | L11: Core | M11: Year-Round | N11: N | O11: Contains Gluten | P11: Middle | Q11: N
A12: ='SKU Master'!A12 -> 07-00011 | B12: =VLOOKUP(A12,'SKU Master'!$A:$N,6,FALSE()) -> Golden Grain Co. Cinnamon Oat Rounds, 14 oz | C12: 4.2 | D12: 7.7 | E12: 3.6 | F12: Upright | G12: N | H12: 2.87 | I12: =('SKU Master'!I12-H12)/'SKU Master'!I12 -> 0.33100233 | J12: 6 | K12: =J12*C12 -> 25.2 | L12: Core | M12: Year-Round | N12: N | O12: Contains Gluten | P12: Eye-Level | Q12: N
A13: ='SKU Master'!A13 -> 07-00012 | B13: =VLOOKUP(A13,'SKU Master'!$A:$N,6,FALSE()) -> Thrift Row Honey Wheat Squares, 14 oz | C13: 4.9 | D13: 6.6 | E13: 4.2 | F13: Upright | G13: Y | H13: 1.99 | I13: =('SKU Master'!I13-H13)/'SKU Master'!I13 -> 0.39513678 | J13: 7 | K13: =J13*C13 -> 34.3 | L13: Core | M13: Year-Round | N13: N | O13: Contains Gluten | P13: Eye-Level | Q13: N
... A5991: ='SKU Master'!A5991 -> 17-00030 | B5991: =VLOOKUP(A5991,'SKU Master'!$A:$N,6,FALSE()) -> Petal & Stem Peace Lily, 4 in | C5991: 6.7 | D5991: 14.5 | E5991: 9 | F5991: Upright | G5991: N | H5991: 4.14 | I5991: =('SKU Master'!I5991-H5991)/'SKU Master'!I5991 -> 0.53430821 | J5991: 5 | K5991: =J5991*C5991 -> 33.5 | L5991: New Item Trial | M5991: Year-Round | N5991: N | O5991: N/A (Non-Food) | P5991: Middle | Q5991: N

Sheet Product Master
A1: UPC (fictional) | B1: GTIN-14 (fictional) | C1: SKU (ref) | D1: Product Name | E1: Brand | F1: Manufacturer | G1: Department | H1: Category | I1: Net Content | J1: Country of Origin | K1: Private Label | L1: Perishable | M1: Units per Case | N1: Suggested Retail Price | O1: Item First Listed
A2: 106992768117 | B2: 00106992768117 | C2: 07-00001 | D2: Redbarn Reduced Sugar Granola Clusters, 18 oz | E2: Redbarn | F2: Redbarn Foods, Inc. | G2: Dry Grocery | H2: Ready-to-Eat Cereal | I2: 18 oz | J2: United States | K2: N | L2: N | M2: 6 | N2: 4.99 | O2: 2026-03-23
A3: 011312704937 | B3: 00011312704937 | C3: 07-00002 | D3: Wheatstone Honey Bran Flakes, 12 oz | E3: Wheatstone | F3: Wheatstone Milling & Baking Co. | G3: Dry Grocery | H3: Ready-to-Eat Cereal | I3: 12 oz | J3: United States | K3: N | L3: N | M3: 1 | N3: 5.99 | O3: 2023-02-17
A4: 214877400000 | B4: 00214877400000 | C4: 07-00003 | D4: Roastport Cinnamon Oat Rounds, 24 oz | E4: Roastport | F4: Roastport Coffee Roasters | G4: Dry Grocery | H4: Ready-to-Eat Cereal | I4: 24 oz | J4: United States | K4: N | L4: N | M4: 24 | N4: 6.89 | O4: 2026-05-03
A5: 492790559772 | B5: 00492790559772 | C5: 07-00004 | D5: Redbarn Frosted Bran Flakes, 10.5 oz | E5: Redbarn | F5: Redbarn Foods, Inc. | G5: Dry Grocery | H5: Ready-to-Eat Cereal | I5: 10.5 oz | J5: United States | K5: N | L5: N | M5: 4 | N5: 3.49 | O5: 2023-02-02
A6: 676749544099 | B6: 00676749544099 | C6: 07-00005 | D6: Roastport Frosted Honey Clusters, 18 oz | E6: Roastport | F6: Roastport Coffee Roasters | G6: Dry Grocery | H6: Ready-to-Eat Cereal | I6: 18 oz | J6: United States | K6: N | L6: N | M6: 12 | N6: 4.39 | O6: 2024-05-27
A7: 496366693740 | B7: 00496366693740 | C7: 07-00006 | D7: Golden Grain Co. Rice Puffs, 12 oz | E7: Golden Grain Co. | F7: Redbarn Foods, Inc. | G7: Dry Grocery | H7: Ready-to-Eat Cereal | I7: 12 oz | J7: United States | K7: N | L7: N | M7: 8 | N7: 4.29 | O7: 2021-06-21
A8: 042924875818 | B8: 00042924875818 | C8: 07-00007 | D8: Orchard Spread Frosted Oat Rounds, 12 oz | E8: Orchard Spread | F8: Orchard Spread Co. | G8: Dry Grocery | H8: Ready-to-Eat Cereal | I8: 12 oz | J8: United States | K8: N | L8: N | M8: 8 | N8: 5.79 | O8: 2025-06-11
A9: 906734906781 | B9: 00906734906781 | C9: 07-00008 | D9: Wheatstone Cinnamon Multigrain Flakes, 18 oz | E9: Wheatstone | F9: Wheatstone Milling & Baking Co. | G9: Dry Grocery | H9: Ready-to-Eat Cereal | I9: 18 oz | J9: Various (imported ingredients) | K9: N | L9: N | M9: 4 | N9: 5.29 | O9: 2022-10-08
A10: 984857893333 | B10: 00984857893333 | C10: 07-00009 | D10: Kettle Row Granola Clusters, 10.5 oz | E10: Kettle Row | F10: Kettle Row Foods, Inc. | G10: Dry Grocery | H10: Ready-to-Eat Cereal | I10: 10.5 oz | J10: United States | K10: N | L10: N | M10: 6 | N10: 3.89 | O10: 2021-09-16
A11: 956823075157 | B11: 00956823075157 | C11: 07-00010 | D11: Nutgrove Honey Oat Rounds, 12 oz | E11: Nutgrove | F11: Nutgrove Snack Group | G11: Dry Grocery | H11: Ready-to-Eat Cereal | I11: 12 oz | J11: United States | K11: N | L11: N | M11: 8 | N11: 5.99 | O11: 2023-02-19
A12: 489010397993 | B12: 00489010397993 | C12: 07-00011 | D12: Golden Grain Co. Cinnamon Oat Rounds, 14 oz | E12: Golden Grain Co. | F12: Redbarn Foods, Inc. | G12: Dry Grocery | H12: Ready-to-Eat Cereal | I12: 14 oz | J12: United States | K12: N | L12: N | M12: 4 | N12: 4.29 | O12: 2021-05-04
A13: 992405326100 | B13: 00992405326100 | C13: 07-00012 | D13: Thrift Row Honey Wheat Squares, 14 oz | E13: Thrift Row | F13: Thrift Row Value Brands (private label) | G13: Dry Grocery | H13: Ready-to-Eat Cereal | I13: 14 oz | J13: United States | K13: Y | L13: N | M13: 6 | N13: 3.29 | O13: 2024-08-29
... A5991: 969395624026 | B5991: 00969395624026 | C5991: 17-00030 | D5991: Petal & Stem Peace Lily, 4 in | E5991: Petal & Stem | F5991: Petal & Stem Growers Cooperative | G5991: Floral | H5991: Potted Plants | I5991: 4 in | J5991: Colombia | K5991: N | L5991: Y | M5991: 1 | N5991: 8.89 | O5991: 2026-07-05

Sheet Department Summary
A1: Department | B1: SKU Count (this file) | C1: Share of File | D1: Grounding / Source
A2: Dry Grocery | B2: 3100 | C2: 0.51752922 | D2: Largest single SKU block by design (center-store assortment of 15,000–30,000 items per store, textbook Ch.1.2); ~52% of this file
A3: Frozen Foods | B3: 420 | C3: 0.070116861 | D3: Anchored to Circana's reported average grocer frozen-SKU count (~1,467 in 2019; Frozen & Refrigerated Buyer, 2024), scaled to file size
A4: Dairy & Eggs | B4: 200 | C4: 0.033388982 | D4: FMI/Progressive Grocer CES: dairy ~9% of department sales
A5: Meat & Seafood | B5: 140 | C5: 0.023372287 | D5: FMI/Progressive Grocer CES: meat/fish/poultry ~13% of sales, but far fewer SKUs than sales share implies (high $/unit)
A6: Produce | B6: 115 | C6: 0.019198664 | D6: FMI/Progressive Grocer CES: produce ~11% of sales
A7: Deli | B7: 70 | C7: 0.011686144 | D7: FMI/Progressive Grocer CES: service + self-service deli ~4.7% of sales
A8: Bakery | B8: 70 | C8: 0.011686144 | D8: FMI/Progressive Grocer CES: baked goods + in-store bakery ~5.3% of sales
A9: Beverages | B9: 255 | C9: 0.042570952 | D9: Generic category-management proportion for shelf-stable beverages
A10: Beer & Wine | B10: 170 | C10: 0.028380634 | D10: Generic proportion where alcohol is licensed for sale
A11: Health & Beauty Care | B11: 400 | C11: 0.066777963 | D11: FMI/Progressive Grocer CES: HBC ~3.5% of sales, high SKU density (many small pack sizes)
A12: Household & Cleaning | B12: 310 | C12: 0.051752922 | D12: Generic proportion for GM/household categories
A13: Paper Goods | B13: 85 | C13: 0.014190317 | D13: Subset of general merchandise/household
... A18: Floral | B18: 30 | C18: 0.0050083472 | D18: FMI/Progressive Grocer CES: floral ~0.02–.19% of sales — smallest department
A19: Total | B19: 5990

Sheet Manufacturer Summary
A1: Manufacturer | B1: Products | C1: Departments Supplied | D1: Private Label?
A2: Harborline Consumer Brands (private label) | B2: 1057 | C2: Baby Care, Bakery, Beverages, Dairy & Eggs, Deli, Dry Grocery, Frozen Foods, General Merchandise, Health & Beauty Care, Household & Cleaning, Meat & Seafood, Paper Goods, Pet Care, Pharmacy / OTC, Produce | D2: Y
A3: Redbarn Foods, Inc. | B3: 643 | C3: Dry Grocery | D3: N
A4: Roastport Coffee Roasters | B4: 317 | C4: Dry Grocery | D4: N
A5: Nutgrove Snack Group | B5: 316 | C5: Dry Grocery | D5: N
A6: Thrift Row Value Brands (private label) | B6: 315 | C6: Dry Grocery | D6: Y
A7: Orchard Spread Co. | B7: 306 | C7: Dry Grocery | D7: N
A8: Kettle Row Foods, Inc. | B8: 302 | C8: Dry Grocery | D8: N
A9: Wheatstone Milling & Baking Co. | B9: 300 | C9: Dry Grocery | D9: N
A10: Pepperlane Sauce Co. | B10: 287 | C10: Dry Grocery | D10: N
A11: IceHarvest Foods Corp. | B11: 114 | C11: Frozen Foods | D11: N
A12: Brightsmile Oral Care Co. | B12: 109 | C12: Health & Beauty Care | D12: N
A13: Northgate Foods Corp. | B13: 108 | C13: Frozen Foods | D13: N
... A50: Millhouse Baking Co. | B50: 22 | C50: Bakery | D50: N

Sheet Methodology & Sources
A1: Workbook structure | B1: Two linked tables. 'Product Master' is the item-level record keyed by UPC (the data a UPC lookup / GS1 data pool / manufacturer item feed would return). 'SKU Master' is the retailer's store-level inventory record. Every product-owned attribute in SKU Master -- Department, Category, Brand, Description, Pack Size, Retail Price, Case Pack, Private Label, Perishable -- is a live VLOOKUP formula keyed on UPC against Product Master, not a duplicated static value. Description is sourced the same way, via VLOOKUP into Product Master's Product Name column (it was the literal text used to build Product Name in the first place, so it belongs to the product, not the store). Store/inventory-only attributes (UOM, Sales Velocity, Reorder Point) are the only ones that remain literal values in SKU Master.
A2: How the lookups work | B2: Each formula reads =VLOOKUP($B{row}, 'Product Master'!$A$2:$O$5991, col_index, FALSE), matching on the UPC in column B of SKU Master against column A of Product Master. Edit a value in Product Master (e.g., Suggested Retail Price for a UPC) and every SKU Master row referencing that UPC updates automatically.
A3: Scope | B3: 5,990 fictional SKUs / product records spanning all 17 departments of a conventional U.S. supermarket. Grounded in FMI's reported 15,000–60,000 SKU range and BLS's ~33,055 national average (2018); this file samples that range proportionally rather than reproducing it exhaustively -- see Department Summary for per-department sourcing.
A4: GTIN-14 | B4: Generated per the standard GS1 convention for converting a 12-digit UPC-A into a 14-digit GTIN: left-pad with two zeros. No digit recalculation is needed or performed.
A5: Manufacturer & Country of Origin | B5: Manufacturers are fictional parent companies mapped from each fictional brand (a few brands share a parent, mirroring real CPG portfolio structure). Country of origin is a weighted random draw using department-level defaults with category-level overrides for wine, imported beer, coffee, and international foods -- illustrative distributions, not sourced from any single retailer's actual import data.
A6: What this file is not | B6: Not real UPCs, not real GS1-registered GTINs, not real manufacturer identities, not real pricing, and not sourced from any retailer's or manufacturer's actual product or item-data feed. All identifiers are randomly generated and any resemblance to real company or product names is coincidental.
A7: Column shading | B7: Rose-shaded columns hold a formula (in SKU Master: Department, Category, Brand, Description, Pack Size, Retail Price, Case Pack, Private Label, Perishable -- each a VLOOKUP into Product Master). Light-green-shaded columns hold a literal, directly-entered value (all of Product Master; and in SKU Master: SKU, UPC, UOM, Sales Velocity, Reorder Point). This shading replaces the previous private-label row highlighting -- filter or sort the Private Label column to find those items instead.
A9: Category Space Allocation sheet:
A10: Per-category linear shelf-space allocation (allocated vs. unallocated, in feet), physical space quality requirements (temperature zone, fixture type, secured/locked case need), and the other attributes category management typically maintains to drive space/facings decisions: category role (destination/routine/occasional-seasonal/convenience), min/max facing rules, sales per linear foot, a space-elasticity coefficient, category-captain status, private-label space target, and reset cadence. SKU Count, Total Category Linear Space, and Space Utilization % are formulas; all other values are fictional but realistic estimates, not sourced retailer data.
A12: SKU Merchandising Attributes sheet:
A13: SKU-level attributes needed to allocate merchandising space to individual SKUs, one row per SKU Master row (aligned 1:1). Covers physical footprint (package dimensions, orientation, stackability), economics (unit cost, gross margin %), the SKU's actual assigned facings and resulting linear space, and assortment/placement attributes (trial/delist status, seasonality, age restriction, allergen flag, shelf level, secondary-display eligibility). SKU and Description are lookups back to SKU Master; Gross Margin % and Current Linear Space Assigned are formulas. All other values are fictional but realistic estimates, not sourced retailer data. Facings and shelf level are weighted by each SKU's sales-velocity rank within its category, bounded by that category's Min/Max Facings per SKU from the Category Space Allocation sheet.
